NonLinLocPy/__init__.py
NonLinLocPy/read_nonlinloc.py
NonLinLocPy-0.0.2.dist-info/LICENSE
NonLinLocPy-0.0.2.dist-info/METADATA
NonLinLocPy-0.0.2.dist-info/WHEEL
NonLinLocPy-0.0.2.dist-info/top_level.txt
NonLinLocPy-0.0.2.dist-info/RECORD
