Metadata-Version: 2.1
Name: NonLinLocPy
Version: 0.0.2
Summary: A package for reading NonLinLoc data into python
Home-page: https://github.com/TomSHudson/
Author: Tom Hudson
Author-email: thomas.hudson@earth.ox.ac.uk
License: UNKNOWN
Platform: UNKNOWN
Classifier: Development Status :: 4 - Beta
Classifier: Programming Language :: Python :: 3
Classifier: License :: OSI Approved :: MIT License
Classifier: Operating System :: OS Independent
